ndradexhyperfine/__init__.py
ndradexhyperfine/bin/.gitignore
ndradexhyperfine/bin/.travis.yml
ndradexhyperfine/bin/LICENSE
ndradexhyperfine/bin/Makefile
ndradexhyperfine/bin/README.md
ndradexhyperfine/db.py
ndradexhyperfine/grid.py
ndradexhyperfine/radex.py
ndradexhyperfine/utils.py
ndradexhyperfine-0.2.6.dist-info/LICENSE
ndradexhyperfine-0.2.6.dist-info/WHEEL
ndradexhyperfine-0.2.6.dist-info/METADATA
ndradexhyperfine-0.2.6.dist-info/RECORD
